requirements.txt
setup.py
github_colors/__init__.py
github_colors.egg-info/PKG-INFO
github_colors.egg-info/SOURCES.txt
github_colors.egg-info/dependency_links.txt
github_colors.egg-info/top_level.txt