Metadata-Version: 2.1
Name: github-colors
Version: 2020.7.1
Summary: Github colors for all the programming languages
Home-page: https://github.com/andrewp-as-is/github-colors.py
License: Unlicense
Keywords: github colors
Platform: UNKNOWN
Classifier: License :: Public Domain
Classifier: Operating System :: OS Independent
Classifier: Programming Language :: Python :: 3
